LICENSE
README.md
setup.cfg
setup.py
jackmartin.parserator.egg-info/PKG-INFO
jackmartin.parserator.egg-info/SOURCES.txt
jackmartin.parserator.egg-info/dependency_links.txt
jackmartin.parserator.egg-info/entry_points.txt
jackmartin.parserator.egg-info/requires.txt
jackmartin.parserator.egg-info/top_level.txt
parserator/__init__.py
parserator/data_prep_utils.py
parserator/main.py
parserator/manual_labeling.py
parserator/parser_template.py
parserator/spotcheck.py
parserator/training.py
parserator/utils.py